[{"content":"Ni yo se sé que pedo conmigo.\n","permalink":"https://crimsonkoba.github.io/blog/about/","summary":"Ni yo se sé que pedo conmigo.","title":"Sobre mi"},{"content":"¿Un tejón melero? Este genial mamífero carnívoro es nativo de África Subsahariana, Oriente Medio e India.\nCon su longitud de hasta un metro y peso máximo de 20kg es conocido cómo el animal más valiente del mundo.\nConsiderado por la revista Scientific American; gramo a gramo el mamífero terrestre más temible de la tierra. Tiene muy pocos depredadores y entres sus victimas se encuentran; hienas, leones, tigres, erizos, cocodrilos\u0026hellip; y no repara en atacar humanos si se siente amenazado. Una de sus comidas favoritas son las serpientes debido a una asombrosa inmunidad al veneno.\nInteligencia Con un cerebro grande en proporción a su cuerpo y la capacidad de utilizar herramientas y la habilidad de resolver problemas complejos lo vuelven en uno de los mamíferos no-primate más inteligente del planeta.\nHoudini de Moholoholo Stoffel fue criado por un agricultor de la zona debido a que era un caos fue llevado al centro de vida salvaje y rehabilitación de Moholoholo en 1996 a la edad de un año y medio. Le fue entregado al fundador de Moholoholo Brian Jones quien rápidamente se encariño con el tejón.\nSe le permitió andar libremente junto a dos hembras de tejón melero. Las hembras eventualmente volvieron a la vida salvaje, pero Stoffel se quedo en cautiverio debido a que había convivido con humanos desde una muy temprana edad y se creía que no sería capaz de adaptarse a la vida salvaje.\nPrimeros pasos Causo estragos en el centro de rehabilitación, matando pequeños ciervos, conejos e incluso una águila leonada adulta.\nTambién visitó el albergue donde echo al personal de la cocina, haciéndose con el control de esta mientras se servia un gran banquete. En otra ocasión visito las habitaciones de los huéspedes, donde esculco entre las pertenencias en busca de algo que le interesara.\nEventualmente fue colocado en un campamento con arboles y césped natural. De donde se escapo para pelear con los leones, terminando en la clínica por dos meses. Después de que Stoffel fuera severamente maltratado, Brian supo que tenia que mantener bajo control a su Tejón.\nFue llevado de vuelta a su territorio donde inmediatamente intento escaparse para volver a pelearse con los leones.\nEl escapista Tras un segundo intento de incursionar en el territorio de los leones, introdujeron a Hammy para ayudarlo a desahogarse pero la cariñosa pareja pronto probo que los tejones meleros no solo son temerarios si no también increíblemente astutos.\nLa puerta del campamento de Stoffel tenia dos cerraduras, ideo un plan, le pide a Hammy que se trepe en el para alcanzar la primer cerradura, quita el alambre que bloqueaba la cerradura y desliza el pasador con sus patas despues sube hasta alcanzar la segunda cerradura y realiza el mismo procedimiento que antes mientras tanto Stoffel sostiene la puerta y la espera para escapar juntos.\nCon tanto empeño en escapar Brian no tuvo mas opción que construirle su propio guantánamo a Stoffel y con el apoyo del Club Rotario le construyeron unos sólidos muros de ladrillo. Sin embargo para sorpresa de los empleados del centro de rehabilitación después de solo unas horas en su nuevo hogar, se volvió a escapar; trepo en los arboles que había dentro y salto desde las ramas hacia los bordes de los muros. Entonces cortaron las ramas y solo dejaron los arboles al centro del campamento pero no fue suficiente para detener a Stoffel desenterró algunas rocas y utilizando sus patas traseras las arrastro hasta una esquina del campamento y las apilo hasta que pudo subir por el muro. Todas las piedras fueron retiradas, pero de nuevo se las arreglo para salir, moldeo bolas de barro y las apilo para volver a salir de ahí y se dirigió a los dormitorios de los empleados del centro de rehabilitación casi como si se estuviera burlando.\nLa historia siguió, utilizaba ramas, instrumentos de limpieza, objetos recreativos y cualquier cosa que le pudiera servir para escapar.\n","permalink":"https://crimsonkoba.github.io/blog/posts/stoffel/","summary":"¿Un tejón melero? Este genial mamífero carnívoro es nativo de África Subsahariana, Oriente Medio e India.\nCon su longitud de hasta un metro y peso máximo de 20kg es conocido cómo el animal más valiente del mundo.\nConsiderado por la revista Scientific American; gramo a gramo el mamífero terrestre más temible de la tierra. Tiene muy pocos depredadores y entres sus victimas se encuentran; hienas, leones, tigres, erizos, cocodrilos\u0026hellip; y no repara en atacar humanos si se siente amenazado.","title":"Stoffel"}]